{
  "moduleName": "buttongroup",
  "description": "A set of Buttons can be displayed together using the ButtonGroup component.\n\n[Live Demo](https://www.primereact.org/button/)",
  "components": {
    "ButtonGroup": {
      "name": "ButtonGroup",
      "description": "",
      "properties": [],
      "callbacks": [],
      "methods": [],
      "stats": {
        "totalProperties": 0,
        "requiredProperties": 0,
        "optionalProperties": 0,
        "callbacksCount": 0,
        "methodsCount": 0
      }
    }
  }
}