{
  "moduleName": "paginator",
  "description": "Paginator is a generic widget to display content in paged format.\n\n[Live Demo](https://www.primereact.org/paginator/)",
  "components": {
    "Paginator": {
      "name": "Paginator",
      "description": "Paginator is a generic widget to display content in paged format.",
      "properties": [
        {
          "name": "alwaysShow",
          "type": "boolean",
          "typeCategory": "boolean",
          "optional": true,
          "readonly": false,
          "defaultValue": null,
          "description": "Whether to show it even there is only one page.",
          "deprecated": null,
          "acceptedValues": [
            true,
            false
          ],
          "formControl": "radio"
        },
        {
          "name": "children",
          "type": "ReactNode",
          "typeCategory": "component",
          "optional": true,
          "readonly": true,
          "defaultValue": null,
          "description": "Used to get the child elements of the component.",
          "deprecated": null,
          "acceptedValues": null,
          "formControl": "template"
        },
        {
          "name": "currentPageReportTemplate",
          "type": "string",
          "typeCategory": "string",
          "optional": true,
          "readonly": false,
          "defaultValue": "({currentPage} of {totalPages})",
          "description": "Template of the current page report element. Available placeholders are {currentPage}, {totalPages}, {rows}, {first}, {last} and {totalRecords}",
          "deprecated": null,
          "acceptedValues": null,
          "formControl": "text"
        },
        {
          "name": "dropdownAppendTo",
          "type": "null | HTMLElement | \"self\" | Function",
          "typeCategory": "component",
          "optional": true,
          "readonly": false,
          "defaultValue": "document.body",
          "description": "DOM element instance where the overlay panel should be mounted. Valid values are any DOM Element and 'self'. The self value is used to render a component where it is located.",
          "deprecated": null,
          "acceptedValues": [
            "self"
          ],
          "formControl": "radio"
        },
        {
          "name": "first",
          "type": "number",
          "typeCategory": "number",
          "optional": true,
          "readonly": false,
          "defaultValue": "0",
          "description": "Zero-relative number of the first row to be displayed.",
          "deprecated": null,
          "acceptedValues": null,
          "formControl": "number"
        },
        {
          "name": "firstPageLinkIcon",
          "type": "IconType<PaginatorProps>",
          "typeCategory": "mixed",
          "optional": true,
          "readonly": false,
          "defaultValue": null,
          "description": "Icon of the first page link icon template.",
          "deprecated": null,
          "acceptedValues": null,
          "formControl": "text"
        },
        {
          "name": "lastPageLinkIcon",
          "type": "IconType<PaginatorProps>",
          "typeCategory": "mixed",
          "optional": true,
          "readonly": false,
          "defaultValue": null,
          "description": "Icon of the last page link icon template.",
          "deprecated": null,
          "acceptedValues": null,
          "formControl": "text"
        },
        {
          "name": "leftContent",
          "type": "ReactNode",
          "typeCategory": "component",
          "optional": true,
          "readonly": false,
          "defaultValue": null,
          "description": "Content to inject into the left side of the paginator.",
          "deprecated": null,
          "acceptedValues": null,
          "formControl": "template"
        },
        {
          "name": "nextPageLinkIcon",
          "type": "IconType<PaginatorProps>",
          "typeCategory": "mixed",
          "optional": true,
          "readonly": false,
          "defaultValue": null,
          "description": "Icon of the next page link icon template.",
          "deprecated": null,
          "acceptedValues": null,
          "formControl": "text"
        },
        {
          "name": "pageLinkSize",
          "type": "number",
          "typeCategory": "number",
          "optional": true,
          "readonly": false,
          "defaultValue": "5",
          "description": "Number of page links to display.",
          "deprecated": null,
          "acceptedValues": null,
          "formControl": "number"
        },
        {
          "name": "prevPageLinkIcon",
          "type": "IconType<PaginatorProps>",
          "typeCategory": "mixed",
          "optional": true,
          "readonly": false,
          "defaultValue": null,
          "description": "Icon of the prev page link icon template.",
          "deprecated": null,
          "acceptedValues": null,
          "formControl": "text"
        },
        {
          "name": "pt",
          "type": "PaginatorPassThroughOptions",
          "typeCategory": "mixed",
          "optional": true,
          "readonly": false,
          "defaultValue": null,
          "description": "Uses to pass attributes to DOM elements inside the component.",
          "deprecated": null,
          "acceptedValues": null,
          "formControl": "text"
        },
        {
          "name": "ptOptions",
          "type": "PassThroughOptions",
          "typeCategory": "mixed",
          "optional": true,
          "readonly": false,
          "defaultValue": null,
          "description": "Used to configure passthrough(pt) options of the component.",
          "deprecated": null,
          "acceptedValues": null,
          "formControl": "text"
        },
        {
          "name": "rightContent",
          "type": "ReactNode",
          "typeCategory": "component",
          "optional": true,
          "readonly": false,
          "defaultValue": null,
          "description": "Content to inject into the right side of the paginator.",
          "deprecated": null,
          "acceptedValues": null,
          "formControl": "template"
        },
        {
          "name": "rows",
          "type": "number",
          "typeCategory": "number",
          "optional": true,
          "readonly": false,
          "defaultValue": "0",
          "description": "Data count to display per page.",
          "deprecated": null,
          "acceptedValues": null,
          "formControl": "number"
        },
        {
          "name": "rowsPerPageOptions",
          "type": "number[]",
          "typeCategory": "array",
          "optional": true,
          "readonly": false,
          "defaultValue": null,
          "description": "Array of integer values to display inside rows per page dropdown.",
          "deprecated": null,
          "acceptedValues": null,
          "formControl": "multiselect"
        },
        {
          "name": "template",
          "type": "string | PaginatorTemplateOptions",
          "typeCategory": "mixed",
          "optional": true,
          "readonly": false,
          "defaultValue": "FirstPageLink PrevPageLink PageLinks NextPageLink LastPageLink RowsPerPageDropdown",
          "description": "Custom template of the paginator.",
          "deprecated": null,
          "acceptedValues": null,
          "formControl": "text"
        },
        {
          "name": "totalRecords",
          "type": "number",
          "typeCategory": "number",
          "optional": true,
          "readonly": false,
          "defaultValue": "0",
          "description": "Number of total records.",
          "deprecated": null,
          "acceptedValues": null,
          "formControl": "number"
        },
        {
          "name": "unstyled",
          "type": "boolean",
          "typeCategory": "boolean",
          "optional": true,
          "readonly": false,
          "defaultValue": "false",
          "description": "When enabled, it removes component related styles in the core.",
          "deprecated": null,
          "acceptedValues": [
            true,
            false
          ],
          "formControl": "radio"
        }
      ],
      "callbacks": [
        {
          "name": "onPageChange",
          "description": "Callback to invoke when page changes, the event object contains information about the new state.",
          "parameters": [
            {
              "name": "event",
              "optional": false,
              "type": "PaginatorPageChangeEvent",
              "description": "Custom page change event."
            }
          ],
          "returnType": "void"
        }
      ],
      "methods": [
        {
          "name": "getElement",
          "description": "Used to get container element.",
          "parameters": [],
          "returnType": "null | HTMLDivElement"
        }
      ],
      "stats": {
        "totalProperties": 19,
        "requiredProperties": 0,
        "optionalProperties": 19,
        "callbacksCount": 1,
        "methodsCount": 1
      }
    }
  }
}